stockwell/_version.py
stockwell/st.py
stockwell/__init__.py
stockwell/sine.py
stockwell/lib_path.py
stockwell/tests/test_stockwell.py
stockwell/tests/__init__.py
stockwell/.dylibs/libfftw3.3.dylib
stockwell/lib/st.cpython-311-darwin.so
stockwell/lib/__init__.py
stockwell/lib/sine.cpython-311-darwin.so
stockwell-1.2.dist-info/RECORD
stockwell-1.2.dist-info/WHEEL
stockwell-1.2.dist-info/top_level.txt
stockwell-1.2.dist-info/LICENSE.txt
stockwell-1.2.dist-info/METADATA
