Metadata-Version: 2.1
Name: stockwell
Version: 1.2
Summary: Time-frequency analysis through Stockwell transform
Home-page: https://github.com/claudiodsf/stockwell
Author: Claudio Satriano
Author-email: satriano@ipgp.fr
License: GNU General Public License v3 or later (GPLv3+)
Project-URL: Homepage, https://github.com/claudiodsf/stockwell
Project-URL: Source, https://github.com/claudiodsf/stockwell
Platform: OS Independent
Classifier: Development Status :: 5 - Production/Stable
Classifier: Environment :: Console
Classifier: Intended Audience :: Science/Research
Classifier: License :: OSI Approved :: GNU General Public License v3 or later (GPLv3+)
Classifier: Operating System :: OS Independent
Classifier: Programming Language :: Python
Classifier: Programming Language :: Python :: 3
Classifier: Programming Language :: Python :: 3.9
Classifier: Programming Language :: Python :: 3.10
Classifier: Programming Language :: Python :: 3.11
Classifier: Programming Language :: Python :: 3.12
Classifier: Programming Language :: Python :: 3.13
Classifier: Topic :: Scientific/Engineering
Classifier: Topic :: Scientific/Engineering :: Physics
License-File: LICENSE.txt
